{"Background": {"1": "AG blue", "2": 135.15}, "Bandages": {"1": "none", "2": 2.5}, "Clothes": {"1": "Leather Black", "2": 26.6}, "Earring": {"1": "none", "2": 3.24}, "Edition": {"1": "none", "2": 1.0}, "Eyes": {"1": "LD SB LBR", "2": 123.47}, "Frame": {"1": "Black", "2": 5.22}, "Fur": {"1": "Black", "2": 12.27}, "Glasses": {"1": "Laser Orange", "2": 178.59}, "Hair": {"1": "ShortH B", "2": 62.9}, "Hats": {"1": "Horn Silver", "2": 44.65}, "Little partner": {"1": "none", "2": 1.15}, "Mouth": {"1": "Detest", "2": 10.94}, "Mouthwear": {"1": "Oxygen Mask Red", "2": 66.23}, "Name": {"1": "none", "2": 1.0}, "Race": {"1": "Human", "2": 2.5}, "Tattoo": {"1": "none", "2": 4.16}, "Type": {"1": "none", "2": 1.0}, "Weapon": {"1": "Sword Blue", "2": 29.85}}